{
  "db_name": "PostgreSQL",
  "query": "SELECT creator_username, title, content, created_at, views FROM pastes WHERE title = $1",
  "describe": {
    "columns": [
      {
        "ordinal": 0,
        "name": "creator_username",
        "type_info": "Varchar"
      },
      {
        "ordinal": 1,
        "name": "title",
        "type_info": "Varchar"
      },
      {
        "ordinal": 2,
        "name": "content",
        "type_info": "Text"
      },
      {
        "ordinal": 3,
        "name": "created_at",
        "type_info": "Int4"
      },
      {
        "ordinal": 4,
        "name": "views",
        "type_info": "Int4"
      }
    ],
    "parameters": {
      "Left": [
        "Text"
      ]
    },
    "nullable": [
      false,
      false,
      false,
      true,
      true
    ]
  },
  "hash": "3ed21cc5b901b6124f8d05bcd0c50c3320d5f8e38a1f64ffdb75e2932da01e70"
}
